wangfusamplepackage/__init__.py
wangfusamplepackage/update_checker.py
wangfusamplepackage/update_package.py
wangfusamplepackage/wangfusamplepackage.py
wangfusamplepackage-0.2.8.dist-info/METADATA
wangfusamplepackage-0.2.8.dist-info/WHEEL
wangfusamplepackage-0.2.8.dist-info/entry_points.txt
wangfusamplepackage-0.2.8.dist-info/top_level.txt
wangfusamplepackage-0.2.8.dist-info/RECORD
