Metadata-Version: 2.2
Name: wangfusamplepackage
Version: 0.2.8
Summary: Quicksample Test Package for SQLShack Demo
Author: Benjamin Wang
Classifier: Programming Language :: Python :: 3
Classifier: License :: OSI Approved :: MIT License
Classifier: Operating System :: OS Independent
Requires-Python: >=3.6
Requires-Dist: argcomplete
Dynamic: author
Dynamic: classifier
Dynamic: description
Dynamic: description-content-type
Dynamic: requires-dist
Dynamic: requires-python
Dynamic: summary
